examples/README.md
examples/__init__.py
examples/config/__init__.py
examples/config/config.yml
examples/run.py
examples/whatsapp/__init__.py
examples/whatsapp/whatsapp_format.py
test/__init__.py
test/resources/config/__init__.py
test/resources/config/config.yml
test/resources/daily_summary/README.md
test/resources/daily_summary/Telegram/README.md
test/resources/daily_summary/Telegram/previous_days.csv
test/resources/daily_summary/Whatsapp/README.md
test/resources/daily_summary/Whatsapp/previous_days.csv
test/resources/daily_summary/Whatsapp/previous_days_before.csv
test/resources/daily_summary/Whatsapp/test_readme_before.md
test/resources/daily_summary/expected_results/Whatsapp/error.md
test/resources/daily_summary/expected_results/Whatsapp/error_with_new_version.md
test/resources/daily_summary/expected_results/Whatsapp/fail.md
test/resources/daily_summary/expected_results/Whatsapp/no_new_version.md
test/resources/daily_summary/expected_results/Whatsapp/no_new_version_empty_string.md
test/resources/daily_summary/expected_results/Whatsapp/no_results.md
test/resources/daily_summary/expected_results/Whatsapp/pass.md
test/resources/daily_summary/expected_results/Whatsapp/previous_days.csv
test/resources/daily_summary/expected_results/all_fail.md
test/resources/daily_summary/expected_results/all_pass.md
test/resources/daily_summary/expected_results/error_and_failed.md
test/resources/daily_summary/expected_results/error_and_no_result.md
test/resources/daily_summary/expected_results/error_and_pass.md
test/resources/daily_summary/expected_results/error_with_new_version_and_pass.md
test/resources/daily_summary/expected_results/fail_and_no_results.md
test/resources/daily_summary/expected_results/no_applications.md
test/resources/daily_summary/expected_results/no_new_versions.md
test/resources/daily_summary/expected_results/no_new_versions_empty_strings.md
test/resources/daily_summary/expected_results/one_fail.md
toucanpy-2.1.0.dist-info/METADATA
toucanpy-2.1.0.dist-info/WHEEL
toucanpy-2.1.0.dist-info/entry_points.txt
toucanpy-2.1.0.dist-info/licenses/LICENSE.txt
toucanpy-2.1.0.dist-info/RECORD
